LICENSE
README.rst
setup.py
async_cache.egg-info/PKG-INFO
async_cache.egg-info/SOURCES.txt
async_cache.egg-info/dependency_links.txt
async_cache.egg-info/top_level.txt
cache/__init__.py
cache/async_lru.py
cache/async_ttl.py
cache/key.py
cache/lru.py
tests/__init__.py
tests/lru_test.py
tests/ttl_test.py