Metadata-Version: 2.1
Name: async-cache
Version: 1.1.0
Summary: An asyncio Cache
Home-page: https://github.com/iamsinghrajat/async-cache
Author: Rajat Singh
Author-email: iamsinghrajat@gmail.com
License: UNKNOWN
Keywords: asyncio,lru,cache,async,cache,lru-cache,ttl
Platform: UNKNOWN
Classifier: Programming Language :: Python :: 3
Classifier: License :: OSI Approved :: MIT License
Classifier: Operating System :: OS Independent
Requires-Python: >=3.3
